elasticsearch/__init__.py
elasticsearch/magic.py
elasticsearch/notebook.py
ipython_elasticsearch-0.2.2.dist-info/DESCRIPTION.rst
ipython_elasticsearch-0.2.2.dist-info/METADATA
ipython_elasticsearch-0.2.2.dist-info/RECORD
ipython_elasticsearch-0.2.2.dist-info/WHEEL
ipython_elasticsearch-0.2.2.dist-info/metadata.json
ipython_elasticsearch-0.2.2.dist-info/top_level.txt
tests/__init__.py
tests/test_magic.py
