Metadata-Version: 2.0
Name: ipython-elasticsearch
Version: 0.2.2
Summary: Elasticearch access via IPython
Home-page: https://pypi.python.org/pypi/ipython-elasticsearch
Author: Gilad Raphaelli
Author-email: g@raphaelli.com
License: MIT
Keywords: database ipython elasticsearch
Platform: UNKNOWN
Classifier: Development Status :: 3 - Alpha
Classifier: Environment :: Console
Classifier: License :: OSI Approved :: MIT License
Classifier: Topic :: Database
Classifier: Topic :: Database :: Front-Ends
Classifier: Programming Language :: Python :: 3
Requires-Dist: requests
